setup.py
t_web_client/__init__.py
t_web_client/http_web_client.py
t_web_client.egg-info/PKG-INFO
t_web_client.egg-info/SOURCES.txt
t_web_client.egg-info/dependency_links.txt
t_web_client.egg-info/top_level.txt
t_web_client.egg-info/zip-safe