Metadata-Version: 1.0
Name: t-web-client
Version: 0.1
Summary: T web client library
Home-page: https://gitlab.com/ddmello/lib/python/t_web_client.git
Author: Darrin D'Mello
Author-email: darrin.dmello@gmail.com
License: MIT
Platform: UNKNOWN
